mlops_training/__init__.py
mlops_training/best_config.py
mlops_training/configs/__init__.py
mlops_training/configs/gridsearch.py
mlops_training/data.py
mlops_training/hyperparameter_tuning.py
mlops_training/models.py
mlops_training/settings.py
mlops_training/train.py
mlops_training/transformers.py
mlops_training/utils.py
mlops_training_pipeline-0.9.0.dist-info/METADATA
mlops_training_pipeline-0.9.0.dist-info/WHEEL
mlops_training_pipeline-0.9.0.dist-info/RECORD
