Metadata-Version: 2.1
Name: mlops_training_pipeline
Version: 0.9.0
Summary: 
Author: CryLake
Author-email: minhchauss123456@gmail.com
Requires-Python: >=3.10,<3.11
Classifier: Programming Language :: Python :: 3
Classifier: Programming Language :: Python :: 3.10
Requires-Dist: Jinja2 (==3.0.1)
Requires-Dist: fire (>=0.5.0,<0.6.0)
Requires-Dist: hopsworks (==3.2.0)
Requires-Dist: lightgbm (>=3.3.5,<4.0.0)
Requires-Dist: matplotlib (>=3.7.1,<4.0.0)
Requires-Dist: pyarrow (>=11.0.0,<12.0.0)
Requires-Dist: python-dotenv (>=1.0.0,<2.0.0)
Requires-Dist: seaborn (>=0.12.2,<0.13.0)
Requires-Dist: sktime (>=0.16.1,<0.17.0)
Requires-Dist: wandb (>=0.14.0,<0.15.0)
